fab_oidc/__init__.py
fab_oidc/security.py
fab_oidc/store.py
fab_oidc/views.py
fab_oidc-0.0.9.dist-info/METADATA
fab_oidc-0.0.9.dist-info/RECORD
fab_oidc-0.0.9.dist-info/WHEEL
fab_oidc-0.0.9.dist-info/top_level.txt
