Metadata-Version: 2.1
Name: fab-oidc
Version: 0.0.9
Summary: Flask-AppBuilder SecurityManager for OpenIDConnect
Home-page: https://github.com/ministryofjustice/fab-oidc/
Author: ministryofjustice
Author-email: dev@digital.justice.gov.uk
License: MIT
Platform: any
Classifier: Development Status :: 3 - Alpha
Classifier: Environment :: Web Environment
Classifier: Intended Audience :: Developers
Classifier: License :: OSI Approved :: MIT License
Classifier: Operating System :: OS Independent
Classifier: Programming Language :: Python
Classifier: Topic :: Software Development :: Libraries :: Python Modules
Classifier: Programming Language :: Python :: 3
Requires-Dist: Flask-AppBuilder (>=1.5.0)
Requires-Dist: Flask-OIDC (>=1.2.0)
Requires-Dist: Flask-Admin (>=1.4.1)
